    <archive path="plugins/com.ibm.icu.source_3.8.1.v20080402.jar" url="http://update.eclipse.org/updates/3.4/plugins/com.ibm.icu.source_3.8.1.v20080402.jar"/>
    <archive path="plugins/com.ibm.icu_3.8.1.v20080402.jar" url="http://update.eclipse.org/updates/3.4/plugins/com.ibm.icu_3.8.1.v20080402.jar"/>
    <archive path="plugins/com.jcraft.jsch_0.1.37.v200803061811.jar" url="http://update.eclipse.org/updates/3.4/plugins/com.jcraft.jsch_0.1.37.v200803061811.jar"/>
    <archive path="plugins/javax.servlet.jsp.source_2.0.0.v200803061910.jar" url="http://update.eclipse.org/updates/3.4/plugins/javax.servlet.jsp.source_2.0.0.v200803061910.jar"/>
    <archive path="plugins/javax.servlet.jsp_2.0.0.v200803061910.jar" url="http://update.eclipse.org/updates/3.4/plugins/javax.servlet.jsp_2.0.0.v200803061910.jar"/>
    <archive path="plugins/javax.servlet.source_2.4.0.v200803061910.jar" url="http://update.eclipse.org/updates/3.4/plugins/javax.servlet.source_2.4.0.v200803061910.jar"/>
    <archive path="plugins/javax.servlet_2.4.0.v200803061910.jar" url="http://update.eclipse.org/updates/3.4/plugins/javax.servlet_2.4.0.v200803061910.jar"/>
    <archive path="plugins/org.apache.ant.source_1.7.0.v200803061910.jar" url="http://update.eclipse.org/updates/3.4/plugins/org.apache.ant.source_1.7.0.v200803061910.jar"/>
    <archive path="plugins/org.apache.commons.el.source_1.0.0.v200803061811.jar" url="http://update.eclipse.org/updates/3.4/plugins/org.apache.commons.el.source_1.0.0.v200803061811.jar"/>
    <archive path="plugins/org.apache.commons.el_1.0.0.v200803061811.jar" url="http://update.eclipse.org/updates/3.4/plugins/org.apache.commons.el_1.0.0.v200803061811.jar"/>
    <archive path="plugins/org.apache.commons.logging.source_1.0.4.v200803061811.jar" url="http://update.eclipse.org/updates/3.4/plugins/org.apache.commons.logging.source_1.0.4.v200803061811.jar"/>
    <archive path="plugins/org.apache.commons.logging_1.0.4.v200803061811.jar" url="http://update.eclipse.org/updates/3.4/plugins/org.apache.commons.logging_1.0.4.v200803061811.jar"/>
    <archive path="plugins/org.apache.jasper.source_5.5.17.v200803061811.jar" url="http://update.eclipse.org/updates/3.4/plugins/org.apache.jasper.source_5.5.17.v200803061811.jar"/>
    <archive path="plugins/org.apache.jasper_5.5.17.v200803061811.jar" url="http://update.eclipse.org/updates/3.4/plugins/org.apache.jasper_5.5.17.v200803061811.jar"/>
    <archive path="plugins/org.apache.lucene.analysis.source_1.9.1.v200803061811.jar" url="http://update.eclipse.org/updates/3.4/plugins/org.apache.lucene.analysis.source_1.9.1.v200803061811.jar"/>
    <archive path="plugins/org.apache.lucene.analysis_1.9.1.v200803061811.jar" url="http://update.eclipse.org/updates/3.4/plugins/org.apache.lucene.analysis_1.9.1.v200803061811.jar"/>
    <archive path="plugins/org.apache.lucene.source_1.9.1.v200803061811.jar" url="http://update.eclipse.org/updates/3.4/plugins/org.apache.lucene.source_1.9.1.v200803061811.jar"/>
    <archive path="plugins/org.apache.lucene_1.9.1.v200803061811.jar" url="http://update.eclipse.org/updates/3.4/plugins/org.apache.lucene_1.9.1.v200803061811.jar"/>
    <archive path="plugins/org.eclipse.ant.core.source_3.2.0.v20080425.jar" url="http://update.eclipse.org/updates/3.4/plugins/org.eclipse.ant.core.source_3.2.0.v20080425.jar"/>
    <archive path="plugins/org.eclipse.ant.core_3.2.0.v20080425.jar" url="http://update.eclipse.org/updates/3.4/plugins/org.eclipse.ant.core_3.2.0.v20080425.jar"/>
    <archive path="plugins/org.eclipse.ant.ui.source_3.3.0.v20080425.jar" url="http://update.eclipse.org/updates/3.4/plugins/org.eclipse.ant.ui.source_3.3.0.v20080425.jar"/>
    <archive path="plugins/org.eclipse.ant.ui_3.3.0.v20080425.jar" url="http://update.eclipse.org/updates/3.4/plugins/org.eclipse.ant.ui_3.3.0.v20080425.jar"/>
    <archive path="plugins/org.eclipse.compare.source_3.4.0.I20080425.jar" url="http://update.eclipse.org/updates/3.4/plugins/org.eclipse.compare.source_3.4.0.I20080425.jar"/>
    <archive path="plugins/org.eclipse.compare_3.4.0.I20080425.jar" url="http://update.eclipse.org/updates/3.4/plugins/org.eclipse.compare_3.4.0.I20080425.jar"/>
    <archive path="plugins/org.eclipse.core.boot_3.1.100.v20080218.jar" url="http://update.eclipse.org/updates/3.4/plugins/org.eclipse.core.boot_3.1.100.v20080218.jar"/>
    <archive path="plugins/org.eclipse.core.commands.source_3.4.0.v20080408-0800.jar" url="http://update.eclipse.org/updates/3.4/plugins/org.eclipse.core.commands.source_3.4.0.v20080408-0800.jar"/>
    <archive path="plugins/org.eclipse.core.commands_3.4.0.v20080408-0800.jar" url="http://update.eclipse.org/updates/3.4/plugins/org.eclipse.core.commands_3.4.0.v20080408-0800.jar"/>
    <archive path="plugins/org.eclipse.core.contenttype.source_3.3.0.v20080414.jar" url="http://update.eclipse.org/updates/3.4/plugins/org.eclipse.core.contenttype.source_3.3.0.v20080414.jar"/>
    <archive path="plugins/org.eclipse.core.contenttype_3.3.0.v20080414.jar" url="http://update.eclipse.org/updates/3.4/plugins/org.eclipse.core.contenttype_3.3.0.v20080414.jar"/>
    <archive path="plugins/org.eclipse.core.databinding.beans.source_1.1.0.I20080425-1551.jar" url="http://update.eclipse.org/updates/3.4/plugins/org.eclipse.core.databinding.beans.source_1.1.0.I20080425-1551.jar"/>
    <archive path="plugins/org.eclipse.core.databinding.beans_1.1.0.I20080425-1551.jar" url="http://update.eclipse.org/updates/3.4/plugins/org.eclipse.core.databinding.beans_1.1.0.I20080425-1551.jar"/>
    <archive path="plugins/org.eclipse.core.databinding.source_1.1.0.I20080425-1551.jar" url="http://update.eclipse.org/updates/3.4/plugins/org.eclipse.core.databinding.source_1.1.0.I20080425-1551.jar"/>
    <archive path="plugins/org.eclipse.core.databinding_1.1.0.I20080425-1551.jar" url="http://update.eclipse.org/updates/3.4/plugins/org.eclipse.core.databinding_1.1.0.I20080425-1551.jar"/>
    <archive path="plugins/org.eclipse.core.expressions.source_3.4.0.v20080430-0100.jar" url="http://update.eclipse.org/updates/3.4/plugins/org.eclipse.core.expressions.source_3.4.0.v20080430-0100.jar"/>
    <archive path="plugins/org.eclipse.core.expressions_3.4.0.v20080430-0100.jar" url="http://update.eclipse.org/updates/3.4/plugins/org.eclipse.core.expressions_3.4.0.v20080430-0100.jar"/>
    <archive path="plugins/org.eclipse.core.filebuffers.source_3.4.0.v20080430-0100.jar" url="http://update.eclipse.org/updates/3.4/plugins/org.eclipse.core.filebuffers.source_3.4.0.v20080430-0100.jar"/>
    <archive path="plugins/org.eclipse.core.filebuffers_3.4.0.v20080430-0100.jar" url="http://update.eclipse.org/updates/3.4/plugins/org.eclipse.core.filebuffers_3.4.0.v20080430-0100.jar"/>
    <archive path="plugins/org.eclipse.core.filesystem.linux.x86_64_1.0.100.v20071126.jar" url="http://update.eclipse.org/updates/3.4/plugins/org.eclipse.core.filesystem.linux.x86_64_1.0.100.v20071126.jar"/>
    <archive path="plugins/org.eclipse.core.filesystem.source_1.2.0.v20080421-1805.jar" url="http://update.eclipse.org/updates/3.4/plugins/org.eclipse.core.filesystem.source_1.2.0.v20080421-1805.jar"/>
    <archive path="plugins/org.eclipse.core.filesystem_1.2.0.v20080421-1805.jar" url="http://update.eclipse.org/updates/3.4/plugins/org.eclipse.core.filesystem_1.2.0.v20080421-1805.jar"/>
    <archive path="plugins/org.eclipse.core.jobs.source_3.4.0.v20080310.jar" url="http://update.eclipse.org/updates/3.4/plugins/org.eclipse.core.jobs.source_3.4.0.v20080310.jar"/>
    <archive path="plugins/org.eclipse.core.jobs_3.4.0.v20080310.jar" url="http://update.eclipse.org/updates/3.4/plugins/org.eclipse.core.jobs_3.4.0.v20080310.jar"/>
    <archive path="plugins/org.eclipse.core.net.source_1.1.0.I20080425.jar" url="http://update.eclipse.org/updates/3.4/plugins/org.eclipse.core.net.source_1.1.0.I20080425.jar"/>
    <archive path="plugins/org.eclipse.core.net_1.1.0.I20080425.jar" url="http://update.eclipse.org/updates/3.4/plugins/org.eclipse.core.net_1.1.0.I20080425.jar"/>
    <archive path="plugins/org.eclipse.core.resources.compatibility.source_3.4.0.v20071204.jar" url="http://update.eclipse.org/updates/3.4/plugins/org.eclipse.core.resources.compatibility.source_3.4.0.v20071204.jar"/>
    <archive path="plugins/org.eclipse.core.resources.compatibility_3.4.0.v20071204.jar" url="http://update.eclipse.org/updates/3.4/plugins/org.eclipse.core.resources.compatibility_3.4.0.v20071204.jar"/>
    <archive path="plugins/org.eclipse.core.resources.source_3.4.0.v20080430-0005.jar" url="http://update.eclipse.org/updates/3.4/plugins/org.eclipse.core.resources.source_3.4.0.v20080430-0005.jar"/>
    <archive path="plugins/org.eclipse.core.resources_3.4.0.v20080430-0005.jar" url="http://update.eclipse.org/updates/3.4/plugins/org.eclipse.core.resources_3.4.0.v20080430-0005.jar"/>
    <archive path="plugins/org.eclipse.core.runtime.compatibility.auth.source_3.2.100.v20070502.jar" url="http://update.eclipse.org/updates/3.4/plugins/org.eclipse.core.runtime.compatibility.auth.source_3.2.100.v20070502.jar"/>
    <archive path="plugins/org.eclipse.core.runtime.compatibility.auth_3.2.100.v20070502.jar" url="http://update.eclipse.org/updates/3.4/plugins/org.eclipse.core.runtime.compatibility.auth_3.2.100.v20070502.jar"/>
    <archive path="plugins/org.eclipse.core.runtime.compatibility.registry.source_3.2.200.v20070717.jar" url="http://update.eclipse.org/updates/3.4/plugins/org.eclipse.core.runtime.compatibility.registry.source_3.2.200.v20070717.jar"/>
    <archive path="plugins/org.eclipse.core.runtime.compatibility.source_3.2.0.v20071008.jar" url="http://update.eclipse.org/updates/3.4/plugins/org.eclipse.core.runtime.compatibility.source_3.2.0.v20071008.jar"/>
    <archive path="plugins/org.eclipse.core.runtime.compatibility_3.2.0.v20071008.jar" url="http://update.eclipse.org/updates/3.4/plugins/org.eclipse.core.runtime.compatibility_3.2.0.v20071008.jar"/>
    <archive path="plugins/org.eclipse.core.runtime.source_3.4.0.v20080421-1805.jar" url="http://update.eclipse.org/updates/3.4/plugins/org.eclipse.core.runtime.source_3.4.0.v20080421-1805.jar"/>
    <archive path="plugins/org.eclipse.core.runtime_3.4.0.v20080421-1805.jar" url="http://update.eclipse.org/updates/3.4/plugins/org.eclipse.core.runtime_3.4.0.v20080421-1805.jar"/>
    <archive path="plugins/org.eclipse.core.variables.source_3.2.100.v20080324-1600.jar" url="http://update.eclipse.org/updates/3.4/plugins/org.eclipse.core.variables.source_3.2.100.v20080324-1600.jar"/>
    <archive path="plugins/org.eclipse.core.variables_3.2.100.v20080324-1600.jar" url="http://update.eclipse.org/updates/3.4/plugins/org.eclipse.core.variables_3.2.100.v20080324-1600.jar"/>
    <archive path="plugins/org.eclipse.cvs.source_1.0.100.v20080324.jar" url="http://update.eclipse.org/updates/3.4/plugins/org.eclipse.cvs.source_1.0.100.v20080324.jar"/>
    <archive path="plugins/org.eclipse.cvs_1.0.100.v20080324.jar" url="http://update.eclipse.org/updates/3.4/plugins/org.eclipse.cvs_1.0.100.v20080324.jar"/>
    <archive path="plugins/org.eclipse.debug.core.source_3.4.0.v20080430-1630.jar" url="http://update.eclipse.org/updates/3.4/plugins/org.eclipse.debug.core.source_3.4.0.v20080430-1630.jar"/>
    <archive path="plugins/org.eclipse.debug.core_3.4.0.v20080430-1630.jar" url="http://update.eclipse.org/updates/3.4/plugins/org.eclipse.debug.core_3.4.0.v20080430-1630.jar"/>
    <archive path="plugins/org.eclipse.debug.ui.source_3.4.0.v20080430-1630.jar" url="http://update.eclipse.org/updates/3.4/plugins/org.eclipse.debug.ui.source_3.4.0.v20080430-1630.jar"/>
    <archive path="plugins/org.eclipse.debug.ui_3.4.0.v20080430-1630.jar" url="http://update.eclipse.org/updates/3.4/plugins/org.eclipse.debug.ui_3.4.0.v20080430-1630.jar"/>
    <archive path="plugins/org.eclipse.ecf.filetransfer_2.0.0.v20080428-0800.jar" url="http://update.eclipse.org/updates/3.4/plugins/org.eclipse.ecf.filetransfer_2.0.0.v20080428-0800.jar"/>
    <archive path="plugins/org.eclipse.ecf.identity_2.0.0.v20080428-0800.jar" url="http://update.eclipse.org/updates/3.4/plugins/org.eclipse.ecf.identity_2.0.0.v20080428-0800.jar"/>
    <archive path="plugins/org.eclipse.ecf.provider.filetransfer.ssl_1.0.0.v20080428-0800.jar" url="http://update.eclipse.org/updates/3.4/plugins/org.eclipse.ecf.provider.filetransfer.ssl_1.0.0.v20080428-0800.jar"/>
    <archive path="plugins/org.eclipse.ecf.provider.filetransfer_2.0.0.v20080428-0800.jar" url="http://update.eclipse.org/updates/3.4/plugins/org.eclipse.ecf.provider.filetransfer_2.0.0.v20080428-0800.jar"/>
    <archive path="plugins/org.eclipse.ecf.ssl_1.0.0.v20080428-0800.jar" url="http://update.eclipse.org/updates/3.4/plugins/org.eclipse.ecf.ssl_1.0.0.v20080428-0800.jar"/>
    <archive path="plugins/org.eclipse.ecf_2.0.0.v20080428-0800.jar" url="http://update.eclipse.org/updates/3.4/plugins/org.eclipse.ecf_2.0.0.v20080428-0800.jar"/>
    <archive path="plugins/org.eclipse.equinox.app.source_1.1.0.v20080421-2006.jar" url="http://update.eclipse.org/updates/3.4/plugins/org.eclipse.equinox.app.source_1.1.0.v20080421-2006.jar"/>
    <archive path="plugins/org.eclipse.equinox.app_1.1.0.v20080421-2006.jar" url="http://update.eclipse.org/updates/3.4/plugins/org.eclipse.equinox.app_1.1.0.v20080421-2006.jar"/>
    <archive path="plugins/org.eclipse.equinox.common.source_3.4.0.v20080421-2006.jar" url="http://update.eclipse.org/updates/3.4/plugins/org.eclipse.equinox.common.source_3.4.0.v20080421-2006.jar"/>
    <archive path="plugins/org.eclipse.equinox.common_3.4.0.v20080421-2006.jar" url="http://update.eclipse.org/updates/3.4/plugins/org.eclipse.equinox.common_3.4.0.v20080421-2006.jar"/>
    <archive path="plugins/org.eclipse.equinox.frameworkadmin.equinox.source_1.0.0.v20080429-2345.jar" url="http://update.eclipse.org/updates/3.4/plugins/org.eclipse.equinox.frameworkadmin.equinox.source_1.0.0.v20080429-2345.jar"/>
    <archive path="plugins/org.eclipse.equinox.frameworkadmin.equinox_1.0.0.v20080429-2345.jar" url="http://update.eclipse.org/updates/3.4/plugins/org.eclipse.equinox.frameworkadmin.equinox_1.0.0.v20080429-2345.jar"/>
    <archive path="plugins/org.eclipse.equinox.frameworkadmin.source_1.0.0.v20080430-1750.jar" url="http://update.eclipse.org/updates/3.4/plugins/org.eclipse.equinox.frameworkadmin.source_1.0.0.v20080430-1750.jar"/>
    <archive path="plugins/org.eclipse.equinox.frameworkadmin_1.0.0.v20080430-1750.jar" url="http://update.eclipse.org/updates/3.4/plugins/org.eclipse.equinox.frameworkadmin_1.0.0.v20080430-1750.jar"/>
    <archive path="plugins/org.eclipse.equinox.http.jetty.source_1.1.0.v20080425.jar" url="http://update.eclipse.org/updates/3.4/plugins/org.eclipse.equinox.http.jetty.source_1.1.0.v20080425.jar"/>
    <archive path="plugins/org.eclipse.equinox.http.jetty_1.1.0.v20080425.jar" url="http://update.eclipse.org/updates/3.4/plugins/org.eclipse.equinox.http.jetty_1.1.0.v20080425.jar"/>
    <archive path="plugins/org.eclipse.equinox.http.registry.source_1.0.100.v20080427-0830.jar" url="http://update.eclipse.org/updates/3.4/plugins/org.eclipse.equinox.http.registry.source_1.0.100.v20080427-0830.jar"/>
    <archive path="plugins/org.eclipse.equinox.http.registry_1.0.100.v20080427-0830.jar" url="http://update.eclipse.org/updates/3.4/plugins/org.eclipse.equinox.http.registry_1.0.100.v20080427-0830.jar"/>
    <archive path="plugins/org.eclipse.equinox.http.servlet.source_1.0.100.v20080427-0830.jar" url="http://update.eclipse.org/updates/3.4/plugins/org.eclipse.equinox.http.servlet.source_1.0.100.v20080427-0830.jar"/>
    <archive path="plugins/org.eclipse.equinox.http.servlet_1.0.100.v20080427-0830.jar" url="http://update.eclipse.org/updates/3.4/plugins/org.eclipse.equinox.http.servlet_1.0.100.v20080427-0830.jar"/>
    <archive path="plugins/org.eclipse.equinox.jsp.jasper.registry.source_1.0.0.v20080427-0830.jar" url="http://update.eclipse.org/updates/3.4/plugins/org.eclipse.equinox.jsp.jasper.registry.source_1.0.0.v20080427-0830.jar"/>
    <archive path="plugins/org.eclipse.equinox.jsp.jasper.registry_1.0.0.v20080427-0830.jar" url="http://update.eclipse.org/updates/3.4/plugins/org.eclipse.equinox.jsp.jasper.registry_1.0.0.v20080427-0830.jar"/>
    <archive path="plugins/org.eclipse.equinox.jsp.jasper.source_1.0.100.v20080427-0830.jar" url="http://update.eclipse.org/updates/3.4/plugins/org.eclipse.equinox.jsp.jasper.source_1.0.100.v20080427-0830.jar"/>
    <archive path="plugins/org.eclipse.equinox.jsp.jasper_1.0.100.v20080427-0830.jar" url="http://update.eclipse.org/updates/3.4/plugins/org.eclipse.equinox.jsp.jasper_1.0.100.v20080427-0830.jar"/>
    <archive path="plugins/org.eclipse.equinox.launcher.source_1.0.100.v20080501.jar" url="http://update.eclipse.org/updates/3.4/plugins/org.eclipse.equinox.launcher.source_1.0.100.v20080501.jar"/>
    <archive path="plugins/org.eclipse.equinox.launcher_1.0.100.v20080501.jar" url="http://update.eclipse.org/updates/3.4/plugins/org.eclipse.equinox.launcher_1.0.100.v20080501.jar"/>
    <archive path="plugins/org.eclipse.equinox.p2.artifact.repository.source_1.0.0.v20080430-1750.jar" url="http://update.eclipse.org/updates/3.4/plugins/org.eclipse.equinox.p2.artifact.repository.source_1.0.0.v20080430-1750.jar"/>
    <archive path="plugins/org.eclipse.equinox.p2.artifact.repository_1.0.0.v20080430-1750.jar" url="http://update.eclipse.org/updates/3.4/plugins/org.eclipse.equinox.p2.artifact.repository_1.0.0.v20080430-1750.jar"/>
    <archive path="plugins/org.eclipse.equinox.p2.console.source_1.0.0.v20080427-2136.jar" url="http://update.eclipse.org/updates/3.4/plugins/org.eclipse.equinox.p2.console.source_1.0.0.v20080427-2136.jar"/>
    <archive path="plugins/org.eclipse.equinox.p2.console_1.0.0.v20080427-2136.jar" url="http://update.eclipse.org/updates/3.4/plugins/org.eclipse.equinox.p2.console_1.0.0.v20080427-2136.jar"/>
    <archive path="plugins/org.eclipse.equinox.p2.core.source_1.0.0.v20080427-2136.jar" url="http://update.eclipse.org/updates/3.4/plugins/org.eclipse.equinox.p2.core.source_1.0.0.v20080427-2136.jar"/>
    <archive path="plugins/org.eclipse.equinox.p2.core_1.0.0.v20080427-2136.jar" url="http://update.eclipse.org/updates/3.4/plugins/org.eclipse.equinox.p2.core_1.0.0.v20080427-2136.jar"/>
    <archive path="plugins/org.eclipse.equinox.p2.director.app.source_1.0.0.v20080430-1250.jar" url="http://update.eclipse.org/updates/3.4/plugins/org.eclipse.equinox.p2.director.app.source_1.0.0.v20080430-1250.jar"/>
    <archive path="plugins/org.eclipse.equinox.p2.director.app_1.0.0.v20080430-1250.jar" url="http://update.eclipse.org/updates/3.4/plugins/org.eclipse.equinox.p2.director.app_1.0.0.v20080430-1250.jar"/>
    <archive path="plugins/org.eclipse.equinox.p2.director.source_1.0.0.v20080428-1800.jar" url="http://update.eclipse.org/updates/3.4/plugins/org.eclipse.equinox.p2.director.source_1.0.0.v20080428-1800.jar"/>
    <archive path="plugins/org.eclipse.equinox.p2.director_1.0.0.v20080428-1800.jar" url="http://update.eclipse.org/updates/3.4/plugins/org.eclipse.equinox.p2.director_1.0.0.v20080428-1800.jar"/>
    <archive path="plugins/org.eclipse.equinox.p2.directorywatcher.source_1.0.0.v20080428-2312.jar" url="http://update.eclipse.org/updates/3.4/plugins/org.eclipse.equinox.p2.directorywatcher.source_1.0.0.v20080428-2312.jar"/>
    <archive path="plugins/org.eclipse.equinox.p2.directorywatcher_1.0.0.v20080428-2312.jar" url="http://update.eclipse.org/updates/3.4/plugins/org.eclipse.equinox.p2.directorywatcher_1.0.0.v20080428-2312.jar"/>
    <archive path="plugins/org.eclipse.equinox.p2.engine.source_1.0.0.v20080428-2312.jar" url="http://update.eclipse.org/updates/3.4/plugins/org.eclipse.equinox.p2.engine.source_1.0.0.v20080428-2312.jar"/>
    <archive path="plugins/org.eclipse.equinox.p2.engine_1.0.0.v20080428-2312.jar" url="http://update.eclipse.org/updates/3.4/plugins/org.eclipse.equinox.p2.engine_1.0.0.v20080428-2312.jar"/>
    <archive path="plugins/org.eclipse.equinox.p2.exemplarysetup.source_1.0.0.v20080427-2136.jar" url="http://update.eclipse.org/updates/3.4/plugins/org.eclipse.equinox.p2.exemplarysetup.source_1.0.0.v20080427-2136.jar"/>
    <archive path="plugins/org.eclipse.equinox.p2.exemplarysetup_1.0.0.v20080427-2136.jar" url="http://update.eclipse.org/updates/3.4/plugins/org.eclipse.equinox.p2.exemplarysetup_1.0.0.v20080427-2136.jar"/>
    <archive path="plugins/org.eclipse.equinox.p2.extensionlocation.source_1.0.0.v20080501-1238.jar" url="http://update.eclipse.org/updates/3.4/plugins/org.eclipse.equinox.p2.extensionlocation.source_1.0.0.v20080501-1238.jar"/>
    <archive path="plugins/org.eclipse.equinox.p2.extensionlocation_1.0.0.v20080501-1238.jar" url="http://update.eclipse.org/updates/3.4/plugins/org.eclipse.equinox.p2.extensionlocation_1.0.0.v20080501-1238.jar"/>
    <archive path="plugins/org.eclipse.equinox.p2.garbagecollector.source_1.0.0.v20080427-2136.jar" url="http://update.eclipse.org/updates/3.4/plugins/org.eclipse.equinox.p2.garbagecollector.source_1.0.0.v20080427-2136.jar"/>
    <archive path="plugins/org.eclipse.equinox.p2.garbagecollector_1.0.0.v20080427-2136.jar" url="http://update.eclipse.org/updates/3.4/plugins/org.eclipse.equinox.p2.garbagecollector_1.0.0.v20080427-2136.jar"/>
    <archive path="plugins/org.eclipse.equinox.p2.jarprocessor.source_1.0.0.v20080427-2136.jar" url="http://update.eclipse.org/updates/3.4/plugins/org.eclipse.equinox.p2.jarprocessor.source_1.0.0.v20080427-2136.jar"/>
    <archive path="plugins/org.eclipse.equinox.p2.jarprocessor_1.0.0.v20080427-2136.jar" url="http://update.eclipse.org/updates/3.4/plugins/org.eclipse.equinox.p2.jarprocessor_1.0.0.v20080427-2136.jar"/>
    <archive path="plugins/org.eclipse.equinox.p2.metadata.generator.source_1.0.0.v20080501-1238.jar" url="http://update.eclipse.org/updates/3.4/plugins/org.eclipse.equinox.p2.metadata.generator.source_1.0.0.v20080501-1238.jar"/>
    <archive path="plugins/org.eclipse.equinox.p2.metadata.generator_1.0.0.v20080501-1238.jar" url="http://update.eclipse.org/updates/3.4/plugins/org.eclipse.equinox.p2.metadata.generator_1.0.0.v20080501-1238.jar"/>
    <archive path="plugins/org.eclipse.equinox.p2.metadata.repository.source_1.0.0.v20080430-1750.jar" url="http://update.eclipse.org/updates/3.4/plugins/org.eclipse.equinox.p2.metadata.repository.source_1.0.0.v20080430-1750.jar"/>
    <archive path="plugins/org.eclipse.equinox.p2.metadata.repository_1.0.0.v20080430-1750.jar" url="http://update.eclipse.org/updates/3.4/plugins/org.eclipse.equinox.p2.metadata.repository_1.0.0.v20080430-1750.jar"/>
    <archive path="plugins/org.eclipse.equinox.p2.metadata.source_1.0.0.v20080427-2136.jar" url="http://update.eclipse.org/updates/3.4/plugins/org.eclipse.equinox.p2.metadata.source_1.0.0.v20080427-2136.jar"/>
    <archive path="plugins/org.eclipse.equinox.p2.metadata_1.0.0.v20080427-2136.jar" url="http://update.eclipse.org/updates/3.4/plugins/org.eclipse.equinox.p2.metadata_1.0.0.v20080427-2136.jar"/>
    <archive path="plugins/org.eclipse.equinox.p2.reconciler.dropins.source_1.0.0.v20080501-1800.jar" url="http://update.eclipse.org/updates/3.4/plugins/org.eclipse.equinox.p2.reconciler.dropins.source_1.0.0.v20080501-1800.jar"/>
    <archive path="plugins/org.eclipse.equinox.p2.reconciler.dropins_1.0.0.v20080501-1800.jar" url="http://update.eclipse.org/updates/3.4/plugins/org.eclipse.equinox.p2.reconciler.dropins_1.0.0.v20080501-1800.jar"/>
    <archive path="plugins/org.eclipse.equinox.p2.touchpoint.eclipse.source_1.0.0.v20080428-1800.jar" url="http://update.eclipse.org/updates/3.4/plugins/org.eclipse.equinox.p2.touchpoint.eclipse.source_1.0.0.v20080428-1800.jar"/>
    <archive path="plugins/org.eclipse.equinox.p2.touchpoint.eclipse_1.0.0.v20080428-1800.jar" url="http://update.eclipse.org/updates/3.4/plugins/org.eclipse.equinox.p2.touchpoint.eclipse_1.0.0.v20080428-1800.jar"/>
    <archive path="plugins/org.eclipse.equinox.p2.touchpoint.natives.source_1.0.0.v20080428-1800.jar" url="http://update.eclipse.org/updates/3.4/plugins/org.eclipse.equinox.p2.touchpoint.natives.source_1.0.0.v20080428-1800.jar"/>
    <archive path="plugins/org.eclipse.equinox.p2.touchpoint.natives_1.0.0.v20080428-1800.jar" url="http://update.eclipse.org/updates/3.4/plugins/org.eclipse.equinox.p2.touchpoint.natives_1.0.0.v20080428-1800.jar"/>
    <archive path="plugins/org.eclipse.equinox.p2.ui.sdk.source_1.0.0.v20080430-1750.jar" url="http://update.eclipse.org/updates/3.4/plugins/org.eclipse.equinox.p2.ui.sdk.source_1.0.0.v20080430-1750.jar"/>
    <archive path="plugins/org.eclipse.equinox.p2.ui.sdk_1.0.0.v20080430-1750.jar" url="http://update.eclipse.org/updates/3.4/plugins/org.eclipse.equinox.p2.ui.sdk_1.0.0.v20080430-1750.jar"/>
    <archive path="plugins/org.eclipse.equinox.p2.ui.source_1.0.0.V20080501-0100.jar" url="http://update.eclipse.org/updates/3.4/plugins/org.eclipse.equinox.p2.ui.source_1.0.0.V20080501-0100.jar"/>
    <archive path="plugins/org.eclipse.equinox.p2.ui_1.0.0.V20080501-0100.jar" url="http://update.eclipse.org/updates/3.4/plugins/org.eclipse.equinox.p2.ui_1.0.0.V20080501-0100.jar"/>
    <archive path="plugins/org.eclipse.equinox.p2.updatechecker.source_1.0.0.v20080427-2136.jar" url="http://update.eclipse.org/updates/3.4/plugins/org.eclipse.equinox.p2.updatechecker.source_1.0.0.v20080427-2136.jar"/>
    <archive path="plugins/org.eclipse.equinox.p2.updatechecker_1.0.0.v20080427-2136.jar" url="http://update.eclipse.org/updates/3.4/plugins/org.eclipse.equinox.p2.updatechecker_1.0.0.v20080427-2136.jar"/>
    <archive path="plugins/org.eclipse.equinox.p2.updatesite.source_1.0.0.v20080430-1750.jar" url="http://update.eclipse.org/updates/3.4/plugins/org.eclipse.equinox.p2.updatesite.source_1.0.0.v20080430-1750.jar"/>
    <archive path="plugins/org.eclipse.equinox.p2.updatesite_1.0.0.v20080430-1750.jar" url="http://update.eclipse.org/updates/3.4/plugins/org.eclipse.equinox.p2.updatesite_1.0.0.v20080430-1750.jar"/>
    <archive path="plugins/org.eclipse.equinox.preferences.source_3.2.200.v20080421-2006.jar" url="http://update.eclipse.org/updates/3.4/plugins/org.eclipse.equinox.preferences.source_3.2.200.v20080421-2006.jar"/>
    <archive path="plugins/org.eclipse.equinox.preferences_3.2.200.v20080421-2006.jar" url="http://update.eclipse.org/updates/3.4/plugins/org.eclipse.equinox.preferences_3.2.200.v20080421-2006.jar"/>
    <archive path="plugins/org.eclipse.equinox.registry.source_3.4.0.v20080421-2006.jar" url="http://update.eclipse.org/updates/3.4/plugins/org.eclipse.equinox.registry.source_3.4.0.v20080421-2006.jar"/>
    <archive path="plugins/org.eclipse.equinox.registry_3.4.0.v20080421-2006.jar" url="http://update.eclipse.org/updates/3.4/plugins/org.eclipse.equinox.registry_3.4.0.v20080421-2006.jar"/>
    <archive path="plugins/org.eclipse.equinox.security.source_1.0.0.v20080430-1700.jar" url="http://update.eclipse.org/updates/3.4/plugins/org.eclipse.equinox.security.source_1.0.0.v20080430-1700.jar"/>
    <archive path="plugins/org.eclipse.equinox.security.ui.source_1.0.0.v20080430-1700.jar" url="http://update.eclipse.org/updates/3.4/plugins/org.eclipse.equinox.security.ui.source_1.0.0.v20080430-1700.jar"/>
    <archive path="plugins/org.eclipse.equinox.security.ui_1.0.0.v20080430-1700.jar" url="http://update.eclipse.org/updates/3.4/plugins/org.eclipse.equinox.security.ui_1.0.0.v20080430-1700.jar"/>
    <archive path="plugins/org.eclipse.equinox.security_1.0.0.v20080430-1700.jar" url="http://update.eclipse.org/updates/3.4/plugins/org.eclipse.equinox.security_1.0.0.v20080430-1700.jar"/>
    <archive path="plugins/org.eclipse.equinox.simpleconfigurator.manipulator.source_1.0.0.v20080427-2136.jar" url="http://update.eclipse.org/updates/3.4/plugins/org.eclipse.equinox.simpleconfigurator.manipulator.source_1.0.0.v20080427-2136.jar"/>
    <archive path="plugins/org.eclipse.equinox.simpleconfigurator.manipulator_1.0.0.v20080427-2136.jar" url="http://update.eclipse.org/updates/3.4/plugins/org.eclipse.equinox.simpleconfigurator.manipulator_1.0.0.v20080427-2136.jar"/>
    <archive path="plugins/org.eclipse.equinox.simpleconfigurator.source_1.0.0.v20080428-1800.jar" url="http://update.eclipse.org/updates/3.4/plugins/org.eclipse.equinox.simpleconfigurator.source_1.0.0.v20080428-1800.jar"/>
    <archive path="plugins/org.eclipse.equinox.simpleconfigurator_1.0.0.v20080428-1800.jar" url="http://update.eclipse.org/updates/3.4/plugins/org.eclipse.equinox.simpleconfigurator_1.0.0.v20080428-1800.jar"/>
    <archive path="plugins/org.eclipse.help.appserver.source_3.1.200.v20070510.jar" url="http://update.eclipse.org/updates/3.4/plugins/org.eclipse.help.appserver.source_3.1.200.v20070510.jar"/>
    <archive path="plugins/org.eclipse.help.appserver_3.1.200.v20070510.jar" url="http://update.eclipse.org/updates/3.4/plugins/org.eclipse.help.appserver_3.1.200.v20070510.jar"/>
    <archive path="plugins/org.eclipse.help.base.source_3.3.100.v20080429.jar" url="http://update.eclipse.org/updates/3.4/plugins/org.eclipse.help.base.source_3.3.100.v20080429.jar"/>
    <archive path="plugins/org.eclipse.help.base_3.3.100.v20080429.jar" url="http://update.eclipse.org/updates/3.4/plugins/org.eclipse.help.base_3.3.100.v20080429.jar"/>
    <archive path="plugins/org.eclipse.help.source_3.3.100.v20080429.jar" url="http://update.eclipse.org/updates/3.4/plugins/org.eclipse.help.source_3.3.100.v20080429.jar"/>
    <archive path="plugins/org.eclipse.help.ui.source_3.3.100.v20080425.jar" url="http://update.eclipse.org/updates/3.4/plugins/org.eclipse.help.ui.source_3.3.100.v20080425.jar"/>
    <archive path="plugins/org.eclipse.help.ui_3.3.100.v20080425.jar" url="http://update.eclipse.org/updates/3.4/plugins/org.eclipse.help.ui_3.3.100.v20080425.jar"/>
    <archive path="plugins/org.eclipse.help.webapp.source_3.3.100.v20080430.jar" url="http://update.eclipse.org/updates/3.4/plugins/org.eclipse.help.webapp.source_3.3.100.v20080430.jar"/>
    <archive path="plugins/org.eclipse.help.webapp_3.3.100.v20080430.jar" url="http://update.eclipse.org/updates/3.4/plugins/org.eclipse.help.webapp_3.3.100.v20080430.jar"/>
    <archive path="plugins/org.eclipse.help_3.3.100.v20080429.jar" url="http://update.eclipse.org/updates/3.4/plugins/org.eclipse.help_3.3.100.v20080429.jar"/>
    <archive path="plugins/org.eclipse.jdt.apt.core.source_3.3.100.v20080430-0240.jar" url="http://update.eclipse.org/updates/3.4/plugins/org.eclipse.jdt.apt.core.source_3.3.100.v20080430-0240.jar"/>
    <archive path="plugins/org.eclipse.jdt.apt.core_3.3.100.v20080430-0240.jar" url="http://update.eclipse.org/updates/3.4/plugins/org.eclipse.jdt.apt.core_3.3.100.v20080430-0240.jar"/>
    <archive path="plugins/org.eclipse.jdt.apt.pluggable.core.source_1.0.100.v20080407-1345.jar" url="http://update.eclipse.org/updates/3.4/plugins/org.eclipse.jdt.apt.pluggable.core.source_1.0.100.v20080407-1345.jar"/>
    <archive path="plugins/org.eclipse.jdt.apt.pluggable.core_1.0.100.v20080407-1345.jar" url="http://update.eclipse.org/updates/3.4/plugins/org.eclipse.jdt.apt.pluggable.core_1.0.100.v20080407-1345.jar"/>
    <archive path="plugins/org.eclipse.jdt.apt.ui.source_3.3.100.v20080407-1345.jar" url="http://update.eclipse.org/updates/3.4/plugins/org.eclipse.jdt.apt.ui.source_3.3.100.v20080407-1345.jar"/>
    <archive path="plugins/org.eclipse.jdt.apt.ui_3.3.100.v20080407-1345.jar" url="http://update.eclipse.org/updates/3.4/plugins/org.eclipse.jdt.apt.ui_3.3.100.v20080407-1345.jar"/>
    <archive path="plugins/org.eclipse.jdt.compiler.apt.source_1.0.100.v20080414-2145.jar" url="http://update.eclipse.org/updates/3.4/plugins/org.eclipse.jdt.compiler.apt.source_1.0.100.v20080414-2145.jar"/>
    <archive path="plugins/org.eclipse.jdt.compiler.apt_1.0.100.v20080414-2145.jar" url="http://update.eclipse.org/updates/3.4/plugins/org.eclipse.jdt.compiler.apt_1.0.100.v20080414-2145.jar"/>
    <archive path="plugins/org.eclipse.jdt.compiler.tool.source_1.0.100.v_858.jar" url="http://update.eclipse.org/updates/3.4/plugins/org.eclipse.jdt.compiler.tool.source_1.0.100.v_858.jar"/>
    <archive path="plugins/org.eclipse.jdt.compiler.tool_1.0.100.v_858.jar" url="http://update.eclipse.org/updates/3.4/plugins/org.eclipse.jdt.compiler.tool_1.0.100.v_858.jar"/>
    <archive path="plugins/org.eclipse.jdt.core.manipulation.source_1.2.0.v20080430-0100.jar" url="http://update.eclipse.org/updates/3.4/plugins/org.eclipse.jdt.core.manipulation.source_1.2.0.v20080430-0100.jar"/>
    <archive path="plugins/org.eclipse.jdt.core.manipulation_1.2.0.v20080430-0100.jar" url="http://update.eclipse.org/updates/3.4/plugins/org.eclipse.jdt.core.manipulation_1.2.0.v20080430-0100.jar"/>
    <archive path="plugins/org.eclipse.jdt.core.source_3.4.0.v_858.jar" url="http://update.eclipse.org/updates/3.4/plugins/org.eclipse.jdt.core.source_3.4.0.v_858.jar"/>
    <archive path="plugins/org.eclipse.jdt.core_3.4.0.v_858.jar" url="http://update.eclipse.org/updates/3.4/plugins/org.eclipse.jdt.core_3.4.0.v_858.jar"/>
    <archive path="plugins/org.eclipse.jdt.debug.source_3.4.0.v20080430-1630.jar" url="http://update.eclipse.org/updates/3.4/plugins/org.eclipse.jdt.debug.source_3.4.0.v20080430-1630.jar"/>
    <archive path="plugins/org.eclipse.jdt.debug.ui.source_3.3.0.v20080430-1630.jar" url="http://update.eclipse.org/updates/3.4/plugins/org.eclipse.jdt.debug.ui.source_3.3.0.v20080430-1630.jar"/>
    <archive path="plugins/org.eclipse.jdt.debug.ui_3.3.0.v20080430-1630.jar" url="http://update.eclipse.org/updates/3.4/plugins/org.eclipse.jdt.debug.ui_3.3.0.v20080430-1630.jar"/>
    <archive path="plugins/org.eclipse.jdt.doc.isv_3.4.0.v20080430-0100.jar" url="http://update.eclipse.org/updates/3.4/plugins/org.eclipse.jdt.doc.isv_3.4.0.v20080430-0100.jar"/>
    <archive path="plugins/org.eclipse.jdt.doc.user_3.4.0.v20080430-0100.jar" url="http://update.eclipse.org/updates/3.4/plugins/org.eclipse.jdt.doc.user_3.4.0.v20080430-0100.jar"/>
    <archive path="plugins/org.eclipse.jdt.junit.runtime.source_3.3.0.v20080430-0100.jar" url="http://update.eclipse.org/updates/3.4/plugins/org.eclipse.jdt.junit.runtime.source_3.3.0.v20080430-0100.jar"/>
    <archive path="plugins/org.eclipse.jdt.junit.runtime_3.3.0.v20080430-0100.jar" url="http://update.eclipse.org/updates/3.4/plugins/org.eclipse.jdt.junit.runtime_3.3.0.v20080430-0100.jar"/>
    <archive path="plugins/org.eclipse.jdt.junit.source_3.4.0.v20080430-0100.jar" url="http://update.eclipse.org/updates/3.4/plugins/org.eclipse.jdt.junit.source_3.4.0.v20080430-0100.jar"/>
    <archive path="plugins/org.eclipse.jdt.junit4.runtime.source_1.0.200.v20080430-0100.jar" url="http://update.eclipse.org/updates/3.4/plugins/org.eclipse.jdt.junit4.runtime.source_1.0.200.v20080430-0100.jar"/>
    <archive path="plugins/org.eclipse.jdt.junit4.runtime_1.0.200.v20080430-0100.jar" url="http://update.eclipse.org/updates/3.4/plugins/org.eclipse.jdt.junit4.runtime_1.0.200.v20080430-0100.jar"/>
    <archive path="plugins/org.eclipse.jdt.junit_3.4.0.v20080430-0100.jar" url="http://update.eclipse.org/updates/3.4/plugins/org.eclipse.jdt.junit_3.4.0.v20080430-0100.jar"/>
    <archive path="plugins/org.eclipse.jdt.launching.source_3.4.0.v20080407.jar" url="http://update.eclipse.org/updates/3.4/plugins/org.eclipse.jdt.launching.source_3.4.0.v20080407.jar"/>
    <archive path="plugins/org.eclipse.jdt.launching_3.4.0.v20080407.jar" url="http://update.eclipse.org/updates/3.4/plugins/org.eclipse.jdt.launching_3.4.0.v20080407.jar"/>
    <archive path="plugins/org.eclipse.jdt.source_3.4.0.v20080430-0100.jar" url="http://update.eclipse.org/updates/3.4/plugins/org.eclipse.jdt.source_3.4.0.v20080430-0100.jar"/>
    <archive path="plugins/org.eclipse.jdt.ui.source_3.4.0.v20080430-0100.jar" url="http://update.eclipse.org/updates/3.4/plugins/org.eclipse.jdt.ui.source_3.4.0.v20080430-0100.jar"/>
    <archive path="plugins/org.eclipse.jdt.ui_3.4.0.v20080430-0100.jar" url="http://update.eclipse.org/updates/3.4/plugins/org.eclipse.jdt.ui_3.4.0.v20080430-0100.jar"/>
    <archive path="plugins/org.eclipse.jdt_3.4.0.v20080430-0100.jar" url="http://update.eclipse.org/updates/3.4/plugins/org.eclipse.jdt_3.4.0.v20080430-0100.jar"/>
    <archive path="plugins/org.eclipse.jface.databinding.source_1.2.0.I20080501-1300.jar" url="http://update.eclipse.org/updates/3.4/plugins/org.eclipse.jface.databinding.source_1.2.0.I20080501-1300.jar"/>
    <archive path="plugins/org.eclipse.jface.databinding_1.2.0.I20080501-1300.jar" url="http://update.eclipse.org/updates/3.4/plugins/org.eclipse.jface.databinding_1.2.0.I20080501-1300.jar"/>
    <archive path="plugins/org.eclipse.jface.source_3.4.0.I20080501-1300a.jar" url="http://update.eclipse.org/updates/3.4/plugins/org.eclipse.jface.source_3.4.0.I20080501-1300a.jar"/>
    <archive path="plugins/org.eclipse.jface.text.source_3.4.0.v20080430-0100.jar" url="http://update.eclipse.org/updates/3.4/plugins/org.eclipse.jface.text.source_3.4.0.v20080430-0100.jar"/>
    <archive path="plugins/org.eclipse.jface.text_3.4.0.v20080430-0100.jar" url="http://update.eclipse.org/updates/3.4/plugins/org.eclipse.jface.text_3.4.0.v20080430-0100.jar"/>
    <archive path="plugins/org.eclipse.jface_3.4.0.I20080501-1300a.jar" url="http://update.eclipse.org/updates/3.4/plugins/org.eclipse.jface_3.4.0.I20080501-1300a.jar"/>
    <archive path="plugins/org.eclipse.jsch.core.source_1.1.100.I20080415.jar" url="http://update.eclipse.org/updates/3.4/plugins/org.eclipse.jsch.core.source_1.1.100.I20080415.jar"/>
    <archive path="plugins/org.eclipse.jsch.core_1.1.100.I20080415.jar" url="http://update.eclipse.org/updates/3.4/plugins/org.eclipse.jsch.core_1.1.100.I20080415.jar"/>
    <archive path="plugins/org.eclipse.jsch.ui.source_1.1.100.I20080415.jar" url="http://update.eclipse.org/updates/3.4/plugins/org.eclipse.jsch.ui.source_1.1.100.I20080415.jar"/>
    <archive path="plugins/org.eclipse.jsch.ui_1.1.100.I20080415.jar" url="http://update.eclipse.org/updates/3.4/plugins/org.eclipse.jsch.ui_1.1.100.I20080415.jar"/>
    <archive path="plugins/org.eclipse.ltk.core.refactoring.source_3.4.0.v20080430-0100.jar" url="http://update.eclipse.org/updates/3.4/plugins/org.eclipse.ltk.core.refactoring.source_3.4.0.v20080430-0100.jar"/>
    <archive path="plugins/org.eclipse.ltk.core.refactoring_3.4.0.v20080430-0100.jar" url="http://update.eclipse.org/updates/3.4/plugins/org.eclipse.ltk.core.refactoring_3.4.0.v20080430-0100.jar"/>
    <archive path="plugins/org.eclipse.ltk.ui.refactoring.source_3.4.0.v20080430-0100.jar" url="http://update.eclipse.org/updates/3.4/plugins/org.eclipse.ltk.ui.refactoring.source_3.4.0.v20080430-0100.jar"/>
    <archive path="plugins/org.eclipse.ltk.ui.refactoring_3.4.0.v20080430-0100.jar" url="http://update.eclipse.org/updates/3.4/plugins/org.eclipse.ltk.ui.refactoring_3.4.0.v20080430-0100.jar"/>
    <archive path="plugins/org.eclipse.osgi.services.source_3.1.200.v20071203.jar" url="http://update.eclipse.org/updates/3.4/plugins/org.eclipse.osgi.services.source_3.1.200.v20071203.jar"/>
    <archive path="plugins/org.eclipse.osgi.services_3.1.200.v20071203.jar" url="http://update.eclipse.org/updates/3.4/plugins/org.eclipse.osgi.services_3.1.200.v20071203.jar"/>
    <archive path="plugins/org.eclipse.osgi.source_3.4.0.v20080427-0830.jar" url="http://update.eclipse.org/updates/3.4/plugins/org.eclipse.osgi.source_3.4.0.v20080427-0830.jar"/>
    <archive path="plugins/org.eclipse.osgi.util.source_3.1.300.v20080303.jar" url="http://update.eclipse.org/updates/3.4/plugins/org.eclipse.osgi.util.source_3.1.300.v20080303.jar"/>
    <archive path="plugins/org.eclipse.osgi.util_3.1.300.v20080303.jar" url="http://update.eclipse.org/updates/3.4/plugins/org.eclipse.osgi.util_3.1.300.v20080303.jar"/>
    <archive path="plugins/org.eclipse.osgi_3.4.0.v20080427-0830.jar" url="http://update.eclipse.org/updates/3.4/plugins/org.eclipse.osgi_3.4.0.v20080427-0830.jar"/>
    <archive path="plugins/org.eclipse.pde.api.tools.source_1.0.0.v20080501-1300.jar" url="http://update.eclipse.org/updates/3.4/plugins/org.eclipse.pde.api.tools.source_1.0.0.v20080501-1300.jar"/>
    <archive path="plugins/org.eclipse.pde.api.tools.ui.source_1.0.0.v20080429-1700.jar" url="http://update.eclipse.org/updates/3.4/plugins/org.eclipse.pde.api.tools.ui.source_1.0.0.v20080429-1700.jar"/>
    <archive path="plugins/org.eclipse.pde.api.tools.ui_1.0.0.v20080429-1700.jar" url="http://update.eclipse.org/updates/3.4/plugins/org.eclipse.pde.api.tools.ui_1.0.0.v20080429-1700.jar"/>
    <archive path="plugins/org.eclipse.pde.api.tools_1.0.0.v20080501-1300.jar" url="http://update.eclipse.org/updates/3.4/plugins/org.eclipse.pde.api.tools_1.0.0.v20080501-1300.jar"/>
    <archive path="plugins/org.eclipse.pde.build.source_3.4.0.v20080430.jar" url="http://update.eclipse.org/updates/3.4/plugins/org.eclipse.pde.build.source_3.4.0.v20080430.jar"/>
    <archive path="plugins/org.eclipse.pde.core.source_3.4.0.v20080430-1001.jar" url="http://update.eclipse.org/updates/3.4/plugins/org.eclipse.pde.core.source_3.4.0.v20080430-1001.jar"/>
    <archive path="plugins/org.eclipse.pde.core_3.4.0.v20080430-1001.jar" url="http://update.eclipse.org/updates/3.4/plugins/org.eclipse.pde.core_3.4.0.v20080430-1001.jar"/>
    <archive path="plugins/org.eclipse.pde.doc.user_3.3.0.v20080429-1700.jar" url="http://update.eclipse.org/updates/3.4/plugins/org.eclipse.pde.doc.user_3.3.0.v20080429-1700.jar"/>
    <archive path="plugins/org.eclipse.pde.junit.runtime.source_3.4.0.v20080428-1100.jar" url="http://update.eclipse.org/updates/3.4/plugins/org.eclipse.pde.junit.runtime.source_3.4.0.v20080428-1100.jar"/>
    <archive path="plugins/org.eclipse.pde.junit.runtime_3.4.0.v20080428-1100.jar" url="http://update.eclipse.org/updates/3.4/plugins/org.eclipse.pde.junit.runtime_3.4.0.v20080428-1100.jar"/>
    <archive path="plugins/org.eclipse.pde.p2.ui.source_1.0.0.v20080428-1100.jar" url="http://update.eclipse.org/updates/3.4/plugins/org.eclipse.pde.p2.ui.source_1.0.0.v20080428-1100.jar"/>
    <archive path="plugins/org.eclipse.pde.p2.ui_1.0.0.v20080428-1100.jar" url="http://update.eclipse.org/updates/3.4/plugins/org.eclipse.pde.p2.ui_1.0.0.v20080428-1100.jar"/>
    <archive path="plugins/org.eclipse.pde.runtime.source_3.4.0.v20080501-1800.jar" url="http://update.eclipse.org/updates/3.4/plugins/org.eclipse.pde.runtime.source_3.4.0.v20080501-1800.jar"/>
    <archive path="plugins/org.eclipse.pde.runtime_3.4.0.v20080501-1800.jar" url="http://update.eclipse.org/updates/3.4/plugins/org.eclipse.pde.runtime_3.4.0.v20080501-1800.jar"/>
    <archive path="plugins/org.eclipse.pde.source_3.4.0.v20080326-1300.jar" url="http://update.eclipse.org/updates/3.4/plugins/org.eclipse.pde.source_3.4.0.v20080326-1300.jar"/>
    <archive path="plugins/org.eclipse.pde.ui.source_3.4.0.v20080501-1300.jar" url="http://update.eclipse.org/updates/3.4/plugins/org.eclipse.pde.ui.source_3.4.0.v20080501-1300.jar"/>
    <archive path="plugins/org.eclipse.pde.ui.templates.source_3.4.0.v20080331-2030.jar" url="http://update.eclipse.org/updates/3.4/plugins/org.eclipse.pde.ui.templates.source_3.4.0.v20080331-2030.jar"/>
    <archive path="plugins/org.eclipse.pde.ui.templates_3.4.0.v20080331-2030.jar" url="http://update.eclipse.org/updates/3.4/plugins/org.eclipse.pde.ui.templates_3.4.0.v20080331-2030.jar"/>
    <archive path="plugins/org.eclipse.pde.ui_3.4.0.v20080501-1300.jar" url="http://update.eclipse.org/updates/3.4/plugins/org.eclipse.pde.ui_3.4.0.v20080501-1300.jar"/>
    <archive path="plugins/org.eclipse.pde_3.4.0.v20080326-1300.jar" url="http://update.eclipse.org/updates/3.4/plugins/org.eclipse.pde_3.4.0.v20080326-1300.jar"/>
    <archive path="plugins/org.eclipse.platform.doc.isv_3.4.0.v20080430-0100a.jar" url="http://update.eclipse.org/updates/3.4/plugins/org.eclipse.platform.doc.isv_3.4.0.v20080430-0100a.jar"/>
    <archive path="plugins/org.eclipse.platform.doc.user_3.4.0.v20080430-0100.jar" url="http://update.eclipse.org/updates/3.4/plugins/org.eclipse.platform.doc.user_3.4.0.v20080430-0100.jar"/>
    <archive path="plugins/org.eclipse.platform.source_3.3.100.v200805020100.jar" url="http://update.eclipse.org/updates/3.4/plugins/org.eclipse.platform.source_3.3.100.v200805020100.jar"/>
    <archive path="plugins/org.eclipse.rcp.source_3.4.0.v20080402.jar" url="http://update.eclipse.org/updates/3.4/plugins/org.eclipse.rcp.source_3.4.0.v20080402.jar"/>
    <archive path="plugins/org.eclipse.rcp_3.4.0.v20080402.jar" url="http://update.eclipse.org/updates/3.4/plugins/org.eclipse.rcp_3.4.0.v20080402.jar"/>
    <archive path="plugins/org.eclipse.search.source_3.4.0.v20080430-0100.jar" url="http://update.eclipse.org/updates/3.4/plugins/org.eclipse.search.source_3.4.0.v20080430-0100.jar"/>
    <archive path="plugins/org.eclipse.search_3.4.0.v20080430-0100.jar" url="http://update.eclipse.org/updates/3.4/plugins/org.eclipse.search_3.4.0.v20080430-0100.jar"/>
    <archive path="plugins/org.eclipse.swt.gtk.linux.x86_64.source_3.4.0.v3442.jar" url="http://update.eclipse.org/updates/3.4/plugins/org.eclipse.swt.gtk.linux.x86_64.source_3.4.0.v3442.jar"/>
    <archive path="plugins/org.eclipse.swt.gtk.linux.x86_64_3.4.0.v3442.jar" url="http://update.eclipse.org/updates/3.4/plugins/org.eclipse.swt.gtk.linux.x86_64_3.4.0.v3442.jar"/>
    <archive path="plugins/org.eclipse.swt_3.4.0.v3442a.jar" url="http://update.eclipse.org/updates/3.4/plugins/org.eclipse.swt_3.4.0.v3442a.jar"/>
    <archive path="plugins/org.eclipse.team.core.source_3.4.0.I20080428.jar" url="http://update.eclipse.org/updates/3.4/plugins/org.eclipse.team.core.source_3.4.0.I20080428.jar"/>
    <archive path="plugins/org.eclipse.team.core_3.4.0.I20080428.jar" url="http://update.eclipse.org/updates/3.4/plugins/org.eclipse.team.core_3.4.0.I20080428.jar"/>
    <archive path="plugins/org.eclipse.team.cvs.core.source_3.3.100.I20080428.jar" url="http://update.eclipse.org/updates/3.4/plugins/org.eclipse.team.cvs.core.source_3.3.100.I20080428.jar"/>
    <archive path="plugins/org.eclipse.team.cvs.core_3.3.100.I20080428.jar" url="http://update.eclipse.org/updates/3.4/plugins/org.eclipse.team.cvs.core_3.3.100.I20080428.jar"/>
    <archive path="plugins/org.eclipse.team.cvs.ssh.source_3.2.100.I20080415.jar" url="http://update.eclipse.org/updates/3.4/plugins/org.eclipse.team.cvs.ssh.source_3.2.100.I20080415.jar"/>
    <archive path="plugins/org.eclipse.team.cvs.ssh2.source_3.2.200.I20080415.jar" url="http://update.eclipse.org/updates/3.4/plugins/org.eclipse.team.cvs.ssh2.source_3.2.200.I20080415.jar"/>
    <archive path="plugins/org.eclipse.team.cvs.ssh2_3.2.200.I20080415.jar" url="http://update.eclipse.org/updates/3.4/plugins/org.eclipse.team.cvs.ssh2_3.2.200.I20080415.jar"/>
    <archive path="plugins/org.eclipse.team.cvs.ssh_3.2.100.I20080415.jar" url="http://update.eclipse.org/updates/3.4/plugins/org.eclipse.team.cvs.ssh_3.2.100.I20080415.jar"/>
    <archive path="plugins/org.eclipse.team.cvs.ui.source_3.3.100.I20080425.jar" url="http://update.eclipse.org/updates/3.4/plugins/org.eclipse.team.cvs.ui.source_3.3.100.I20080425.jar"/>
    <archive path="plugins/org.eclipse.team.cvs.ui_3.3.100.I20080425.jar" url="http://update.eclipse.org/updates/3.4/plugins/org.eclipse.team.cvs.ui_3.3.100.I20080425.jar"/>
    <archive path="plugins/org.eclipse.team.ui.source_3.4.0.I20080422.jar" url="http://update.eclipse.org/updates/3.4/plugins/org.eclipse.team.ui.source_3.4.0.I20080422.jar"/>
    <archive path="plugins/org.eclipse.team.ui_3.4.0.I20080422.jar" url="http://update.eclipse.org/updates/3.4/plugins/org.eclipse.team.ui_3.4.0.I20080422.jar"/>
    <archive path="plugins/org.eclipse.text.source_3.4.0.v20080430-0100.jar" url="http://update.eclipse.org/updates/3.4/plugins/org.eclipse.text.source_3.4.0.v20080430-0100.jar"/>
    <archive path="plugins/org.eclipse.text_3.4.0.v20080430-0100.jar" url="http://update.eclipse.org/updates/3.4/plugins/org.eclipse.text_3.4.0.v20080430-0100.jar"/>
    <archive path="plugins/org.eclipse.ui.browser.source_3.2.200.v20080407.jar" url="http://update.eclipse.org/updates/3.4/plugins/org.eclipse.ui.browser.source_3.2.200.v20080407.jar"/>
    <archive path="plugins/org.eclipse.ui.browser_3.2.200.v20080407.jar" url="http://update.eclipse.org/updates/3.4/plugins/org.eclipse.ui.browser_3.2.200.v20080407.jar"/>
    <archive path="plugins/org.eclipse.ui.cheatsheets.source_3.3.100.v20080421.jar" url="http://update.eclipse.org/updates/3.4/plugins/org.eclipse.ui.cheatsheets.source_3.3.100.v20080421.jar"/>
    <archive path="plugins/org.eclipse.ui.cheatsheets_3.3.100.v20080421.jar" url="http://update.eclipse.org/updates/3.4/plugins/org.eclipse.ui.cheatsheets_3.3.100.v20080421.jar"/>
    <archive path="plugins/org.eclipse.ui.console.source_3.3.0.v20080425.jar" url="http://update.eclipse.org/updates/3.4/plugins/org.eclipse.ui.console.source_3.3.0.v20080425.jar"/>
    <archive path="plugins/org.eclipse.ui.console_3.3.0.v20080425.jar" url="http://update.eclipse.org/updates/3.4/plugins/org.eclipse.ui.console_3.3.0.v20080425.jar"/>
    <archive path="plugins/org.eclipse.ui.editors.source_3.4.0.v20080430-0100.jar" url="http://update.eclipse.org/updates/3.4/plugins/org.eclipse.ui.editors.source_3.4.0.v20080430-0100.jar"/>
    <archive path="plugins/org.eclipse.ui.editors_3.4.0.v20080430-0100.jar" url="http://update.eclipse.org/updates/3.4/plugins/org.eclipse.ui.editors_3.4.0.v20080430-0100.jar"/>
    <archive path="plugins/org.eclipse.ui.externaltools.source_3.2.0.v20080407.jar" url="http://update.eclipse.org/updates/3.4/plugins/org.eclipse.ui.externaltools.source_3.2.0.v20080407.jar"/>
    <archive path="plugins/org.eclipse.ui.externaltools_3.2.0.v20080407.jar" url="http://update.eclipse.org/updates/3.4/plugins/org.eclipse.ui.externaltools_3.2.0.v20080407.jar"/>
    <archive path="plugins/org.eclipse.ui.forms.source_3.3.100.v20080414.jar" url="http://update.eclipse.org/updates/3.4/plugins/org.eclipse.ui.forms.source_3.3.100.v20080414.jar"/>
    <archive path="plugins/org.eclipse.ui.forms_3.3.100.v20080414.jar" url="http://update.eclipse.org/updates/3.4/plugins/org.eclipse.ui.forms_3.3.100.v20080414.jar"/>
    <archive path="plugins/org.eclipse.ui.ide.application.source_1.0.0.I20080501-1300.jar" url="http://update.eclipse.org/updates/3.4/plugins/org.eclipse.ui.ide.application.source_1.0.0.I20080501-1300.jar"/>
    <archive path="plugins/org.eclipse.ui.ide.application_1.0.0.I20080501-1300.jar" url="http://update.eclipse.org/updates/3.4/plugins/org.eclipse.ui.ide.application_1.0.0.I20080501-1300.jar"/>
    <archive path="plugins/org.eclipse.ui.ide.source_3.4.0.I20080430-1800.jar" url="http://update.eclipse.org/updates/3.4/plugins/org.eclipse.ui.ide.source_3.4.0.I20080430-1800.jar"/>
    <archive path="plugins/org.eclipse.ui.ide_3.4.0.I20080430-1800.jar" url="http://update.eclipse.org/updates/3.4/plugins/org.eclipse.ui.ide_3.4.0.I20080430-1800.jar"/>
    <archive path="plugins/org.eclipse.ui.intro.source_3.2.200.v20080421.jar" url="http://update.eclipse.org/updates/3.4/plugins/org.eclipse.ui.intro.source_3.2.200.v20080421.jar"/>
    <archive path="plugins/org.eclipse.ui.intro.universal.source_3.2.200.v20080425.jar" url="http://update.eclipse.org/updates/3.4/plugins/org.eclipse.ui.intro.universal.source_3.2.200.v20080425.jar"/>
    <archive path="plugins/org.eclipse.ui.intro_3.2.200.v20080421.jar" url="http://update.eclipse.org/updates/3.4/plugins/org.eclipse.ui.intro_3.2.200.v20080421.jar"/>
    <archive path="plugins/org.eclipse.ui.navigator.resources.source_3.3.100.I20080425-1551.jar" url="http://update.eclipse.org/updates/3.4/plugins/org.eclipse.ui.navigator.resources.source_3.3.100.I20080425-1551.jar"/>
    <archive path="plugins/org.eclipse.ui.navigator.resources_3.3.100.I20080425-1551.jar" url="http://update.eclipse.org/updates/3.4/plugins/org.eclipse.ui.navigator.resources_3.3.100.I20080425-1551.jar"/>
    <archive path="plugins/org.eclipse.ui.navigator.source_3.3.100.I20080422-0800.jar" url="http://update.eclipse.org/updates/3.4/plugins/org.eclipse.ui.navigator.source_3.3.100.I20080422-0800.jar"/>
    <archive path="plugins/org.eclipse.ui.navigator_3.3.100.I20080422-0800.jar" url="http://update.eclipse.org/updates/3.4/plugins/org.eclipse.ui.navigator_3.3.100.I20080422-0800.jar"/>
    <archive path="plugins/org.eclipse.ui.net.source_1.0.0.I20080415.jar" url="http://update.eclipse.org/updates/3.4/plugins/org.eclipse.ui.net.source_1.0.0.I20080415.jar"/>
    <archive path="plugins/org.eclipse.ui.net_1.0.0.I20080415.jar" url="http://update.eclipse.org/updates/3.4/plugins/org.eclipse.ui.net_1.0.0.I20080415.jar"/>
    <archive path="plugins/org.eclipse.ui.presentations.r21.source_3.2.100.v20080408-0800.jar" url="http://update.eclipse.org/updates/3.4/plugins/org.eclipse.ui.presentations.r21.source_3.2.100.v20080408-0800.jar"/>
    <archive path="plugins/org.eclipse.ui.presentations.r21_3.2.100.v20080408-0800.jar" url="http://update.eclipse.org/updates/3.4/plugins/org.eclipse.ui.presentations.r21_3.2.100.v20080408-0800.jar"/>
    <archive path="plugins/org.eclipse.ui.source_3.4.0.I20080501-1300a.jar" url="http://update.eclipse.org/updates/3.4/plugins/org.eclipse.ui.source_3.4.0.I20080501-1300a.jar"/>
    <archive path="plugins/org.eclipse.ui.views.log.source_1.0.0.v20080422-0800.jar" url="http://update.eclipse.org/updates/3.4/plugins/org.eclipse.ui.views.log.source_1.0.0.v20080422-0800.jar"/>
    <archive path="plugins/org.eclipse.ui.views.log_1.0.0.v20080422-0800.jar" url="http://update.eclipse.org/updates/3.4/plugins/org.eclipse.ui.views.log_1.0.0.v20080422-0800.jar"/>
    <archive path="plugins/org.eclipse.ui.views.properties.tabbed.source_3.4.0.I20080422-0800.jar" url="http://update.eclipse.org/updates/3.4/plugins/org.eclipse.ui.views.properties.tabbed.source_3.4.0.I20080422-0800.jar"/>
    <archive path="plugins/org.eclipse.ui.views.properties.tabbed_3.4.0.I20080422-0800.jar" url="http://update.eclipse.org/updates/3.4/plugins/org.eclipse.ui.views.properties.tabbed_3.4.0.I20080422-0800.jar"/>
    <archive path="plugins/org.eclipse.ui.views.source_3.3.0.I20080501-1300a.jar" url="http://update.eclipse.org/updates/3.4/plugins/org.eclipse.ui.views.source_3.3.0.I20080501-1300a.jar"/>
    <archive path="plugins/org.eclipse.ui.views_3.3.0.I20080501-1300a.jar" url="http://update.eclipse.org/updates/3.4/plugins/org.eclipse.ui.views_3.3.0.I20080501-1300a.jar"/>
    <archive path="plugins/org.eclipse.ui.workbench.compatibility.source_3.2.0.v20080408-0800.jar" url="http://update.eclipse.org/updates/3.4/plugins/org.eclipse.ui.workbench.compatibility.source_3.2.0.v20080408-0800.jar"/>
    <archive path="plugins/org.eclipse.ui.workbench.source_3.4.0.I20080501-0100.jar" url="http://update.eclipse.org/updates/3.4/plugins/org.eclipse.ui.workbench.source_3.4.0.I20080501-0100.jar"/>
    <archive path="plugins/org.eclipse.ui.workbench.texteditor.source_3.4.0.v20080430-0100.jar" url="http://update.eclipse.org/updates/3.4/plugins/org.eclipse.ui.workbench.texteditor.source_3.4.0.v20080430-0100.jar"/>
    <archive path="plugins/org.eclipse.ui.workbench.texteditor_3.4.0.v20080430-0100.jar" url="http://update.eclipse.org/updates/3.4/plugins/org.eclipse.ui.workbench.texteditor_3.4.0.v20080430-0100.jar"/>
    <archive path="plugins/org.eclipse.ui.workbench_3.4.0.I20080501-0100.jar" url="http://update.eclipse.org/updates/3.4/plugins/org.eclipse.ui.workbench_3.4.0.I20080501-0100.jar"/>
    <archive path="plugins/org.eclipse.ui_3.4.0.I20080501-1300a.jar" url="http://update.eclipse.org/updates/3.4/plugins/org.eclipse.ui_3.4.0.I20080501-1300a.jar"/>
    <archive path="plugins/org.eclipse.update.configurator.source_3.2.200.v20080417.jar" url="http://update.eclipse.org/updates/3.4/plugins/org.eclipse.update.configurator.source_3.2.200.v20080417.jar"/>
    <archive path="plugins/org.eclipse.update.configurator_3.2.200.v20080417.jar" url="http://update.eclipse.org/updates/3.4/plugins/org.eclipse.update.configurator_3.2.200.v20080417.jar"/>
    <archive path="plugins/org.eclipse.update.core.linux.source_3.2.0.v20080422.jar" url="http://update.eclipse.org/updates/3.4/plugins/org.eclipse.update.core.linux.source_3.2.0.v20080422.jar"/>
    <archive path="plugins/org.eclipse.update.core.linux_3.2.0.v20080422.jar" url="http://update.eclipse.org/updates/3.4/plugins/org.eclipse.update.core.linux_3.2.0.v20080422.jar"/>
    <archive path="plugins/org.eclipse.update.core.source_3.2.200.v20080428.jar" url="http://update.eclipse.org/updates/3.4/plugins/org.eclipse.update.core.source_3.2.200.v20080428.jar"/>
    <archive path="plugins/org.eclipse.update.core_3.2.200.v20080428.jar" url="http://update.eclipse.org/updates/3.4/plugins/org.eclipse.update.core_3.2.200.v20080428.jar"/>
    <archive path="plugins/org.eclipse.update.scheduler.source_3.2.100.v20080404.jar" url="http://update.eclipse.org/updates/3.4/plugins/org.eclipse.update.scheduler.source_3.2.100.v20080404.jar"/>
    <archive path="plugins/org.eclipse.update.scheduler_3.2.100.v20080404.jar" url="http://update.eclipse.org/updates/3.4/plugins/org.eclipse.update.scheduler_3.2.100.v20080404.jar"/>
    <archive path="plugins/org.eclipse.update.ui.source_3.2.100.v20080318.jar" url="http://update.eclipse.org/updates/3.4/plugins/org.eclipse.update.ui.source_3.2.100.v20080318.jar"/>
    <archive path="plugins/org.eclipse.update.ui_3.2.100.v20080318.jar" url="http://update.eclipse.org/updates/3.4/plugins/org.eclipse.update.ui_3.2.100.v20080318.jar"/>
    <archive path="plugins/org.junit.source_3.8.2.v20080327.jar" url="http://update.eclipse.org/updates/3.4/plugins/org.junit.source_3.8.2.v20080327.jar"/>
    <archive path="plugins/org.junit4.source_4.3.1.jar" url="http://update.eclipse.org/updates/3.4/plugins/org.junit4.source_4.3.1.jar"/>
    <archive path="plugins/org.mortbay.jetty.source_5.1.14.v200804221617.jar" url="http://update.eclipse.org/updates/3.4/plugins/org.mortbay.jetty.source_5.1.14.v200804221617.jar"/>
    <archive path="plugins/org.mortbay.jetty_5.1.14.v200804221617.jar" url="http://update.eclipse.org/updates/3.4/plugins/org.mortbay.jetty_5.1.14.v200804221617.jar"/>
    <archive path="plugins/org.objectweb.asm.source_3.1.0.v200803061910.jar" url="http://update.eclipse.org/updates/3.4/plugins/org.objectweb.asm.source_3.1.0.v200803061910.jar"/>
    <archive path="plugins/org.objectweb.asm_3.1.0.v200803061910.jar" url="http://update.eclipse.org/updates/3.4/plugins/org.objectweb.asm_3.1.0.v200803061910.jar"/>
    <archive path="plugins/org.sat4j.core_2.0.0.v20080430.jar" url="http://update.eclipse.org/updates/3.4/plugins/org.sat4j.core_2.0.0.v20080430.jar"/>
    <archive path="plugins/org.sat4j.pb_2.0.0.v20080430.jar" url="http://update.eclipse.org/updates/3.4/plugins/org.sat4j.pb_2.0.0.v20080430.jar"/>
    <archive path="plugins/org.apache.ant_1.7.0.v200803061910.jar" url="http://update.eclipse.org/updates/3.4/plugins/org.apache.ant_1.7.0.v200803061910.jar"/>
    <archive path="plugins/org.apache.commons.codec_1.3.0.v200803061910.jar" url="http://update.eclipse.org/updates/3.4/plugins/org.apache.commons.codec_1.3.0.v200803061910.jar"/>
    <archive path="plugins/org.apache.commons.httpclient_3.1.0.v200803061910.jar" url="http://update.eclipse.org/updates/3.4/plugins/org.apache.commons.httpclient_3.1.0.v200803061910.jar"/>
    <archive path="plugins/org.eclipse.core.runtime.compatibility.registry_3.2.200.v20070717.jar" url="http://update.eclipse.org/updates/3.4/plugins/org.eclipse.core.runtime.compatibility.registry_3.2.200.v20070717.jar"/>
    <archive path="plugins/org.eclipse.equinox.launcher.gtk.linux.x86_64_1.0.100.v20080428-1330.jar" url="http://update.eclipse.org/updates/3.4/plugins/org.eclipse.equinox.launcher.gtk.linux.x86_64_1.0.100.v20080428-1330.jar"/>
    <archive path="plugins/org.eclipse.jdt.debug_3.4.0.v20080430-1630.jar" url="http://update.eclipse.org/updates/3.4/plugins/org.eclipse.jdt.debug_3.4.0.v20080430-1630.jar"/>
    <archive path="plugins/org.eclipse.pde.build_3.4.0.v20080430.jar" url="http://update.eclipse.org/updates/3.4/plugins/org.eclipse.pde.build_3.4.0.v20080430.jar"/>
    <archive path="plugins/org.eclipse.platform_3.3.100.v200805020100.jar" url="http://update.eclipse.org/updates/3.4/plugins/org.eclipse.platform_3.3.100.v200805020100.jar"/>
    <archive path="plugins/org.eclipse.sdk_3.4.0.v200805020100.jar" url="http://update.eclipse.org/updates/3.4/plugins/org.eclipse.sdk_3.4.0.v200805020100.jar"/>
    <archive path="plugins/org.eclipse.ui.intro.universal_3.2.200.v20080425.jar" url="http://update.eclipse.org/updates/3.4/plugins/org.eclipse.ui.intro.universal_3.2.200.v20080425.jar"/>
    <archive path="plugins/org.eclipse.ui.workbench.compatibility_3.2.0.v20080408-0800.jar" url="http://update.eclipse.org/updates/3.4/plugins/org.eclipse.ui.workbench.compatibility_3.2.0.v20080408-0800.jar"/>
    <archive path="plugins/org.junit4_4.3.1.jar" url="http://update.eclipse.org/updates/3.4/plugins/org.junit4_4.3.1.jar"/>
    <archive path="plugins/org.junit_3.8.2.v20080327.jar" url="http://update.eclipse.org/updates/3.4/plugins/org.junit_3.8.2.v20080327.jar"/>
    <archive path="plugins/org.tigris.subversion.subclipse.core_1.2.4.jar" url="http://subclipse.tigris.org/update_1.2.x/plugins/org.tigris.subversion.subclipse.core_1.2.4.jar"/>
    <archive path="plugins/org.tigris.subversion.subclipse.doc_1.2.0.jar" url="http://subclipse.tigris.org/update_1.2.x/plugins/org.tigris.subversion.subclipse.doc_1.2.0.jar"/>
    <archive path="plugins/org.tigris.subversion.subclipse.ui_1.2.4.jar" url="http://subclipse.tigris.org/update_1.2.x/plugins/org.tigris.subversion.subclipse.ui_1.2.4.jar"/>



